<?xml version="1.0" encoding="UTF-8"?>
<objects serializationModel="Studio.02.00.00">
	<object class="AudioFile" id="{fde38eb5-c836-4724-b854-3e3a12b96945}">
		<property name="assetPath">
			<value>all_who_enter_perish.wav</value>
		</property>
		<property name="frequencyInKHz">
			<value>48</value>
		</property>
		<property name="channelCount">
			<value>2</value>
		</property>
		<property name="length">
			<value>7.3258958333333331</value>
		</property>
		<relationship name="masterAssetFolder">
			<destination>{ec1b0f61-fb5c-4b9e-b9b5-49ac8899c82c}</destination>
		</relationship>
	</object>
</objects>
